<?xml version="1.0" encoding="utf-8" ?>
<eveHQUpdate>
  <lastUpdated>07/10/2009 21:00:00</lastUpdated>
  <files>
    <file>
      <name>EveHQ.exe</name>
      <type>Required</type>
      <version>1.13.2.1022</version>
      <hasDebug>True</hasDebug>
      <description>EveHQ Executable</description>
    </file>
    <file>
      <name>EveHQ.Core.dll</name>
      <type>Required</type>
      <version>1.13.2.1022</version>
      <hasDebug>True</hasDebug>
      <description>EveHQ Core Library</description>
    </file>
    <file>
      <name>EveHQ.CoreControls.dll</name>
      <type>Required</type>
      <version>1.13.2.1022</version>
      <hasDebug>True</hasDebug>
      <description>EveHQ Controls Library</description>
    </file>
    <file>
      <name>EveHQ.mdb.zip</name>
      <type>Required</type>
      <version>1.13.0.0</version>
      <hasDebug>False</hasDebug>
      <description>EveHQ Access Database</description>
    </file>
    <file_t>
      <name>LgLcd.NET.dll</name>
      <type>Required</type>
      <version>1.0.2182.20042</version>
      <hasDebug>False</hasDebug>
      <description>G15 LCD .Net Wrapper Library</description>
    </file_t>
    <file_t>
      <name>LgLcd.dll</name>
      <type>Required</type>
      <version>Any</version>
      <hasDebug>False</hasDebug>
      <description>G15 LCD Library</description>
    </file_t>
    <file>
      <name>EveHQ.CorpHQ.dll</name>
      <type>Plug-in</type>
      <version>1.13.0.805</version>
      <hasDebug>True</hasDebug>
      <description>Corp Management Plug-in</description>
    </file>
    <file>
      <name>EveHQ.Creation.dll</name>
      <type>Plug-in</type>
      <version>1.13.2.895</version>
      <hasDebug>True</hasDebug>
      <description>Character Creation Plug-in</description>
    </file>
    <file_t>
      <name>EveHQ.DataConverter.dll</name>
      <type>Plug-in</type>
      <version>1.13.0.805</version>
      <hasDebug>True</hasDebug>
      <description>Data Converter Plug-in</description>
    </file_t>
    <file>
      <name>EveHQ.ItemBrowser.dll</name>
      <type>Plug-in</type>
      <version>1.13.2.1021</version>
      <hasDebug>True</hasDebug>
      <description>Item Browser Plug-in</description>
    </file>
    <file>
      <name>EveHQ.KillMailViewer.dll</name>
      <type>Plug-in</type>
      <version>1.13.0.805</version>
      <hasDebug>True</hasDebug>
      <description>Killmail Viewer and Parser</description>
    </file>
    <file>
      <name>EveHQ.Map.dll</name>
      <type>Plug-in</type>
      <version>1.13.2.1021</version>
      <hasDebug>True</hasDebug>
      <description>Map and Routing Plug-in</description>
    </file>
    <file>
      <name>EveHQ.HQF.dll</name>
      <type>Plug-in</type>
      <version>1.13.2.1021</version>
      <hasDebug>True</hasDebug>
      <description>Ship Fitting Plug-in</description>
    </file>
    <file>
      <name>EveHQ.Prism.dll</name>
      <type>Plug-in</type>
      <version>1.13.2.1021</version>
      <hasDebug>True</hasDebug>
      <description>Science and Industry Plug-in</description>
    </file>
    <file>
      <name>EveHQ.PosManager.dll</name>
      <type>Plug-in</type>
      <version>1.13.2.1021</version>
      <hasDebug>True</hasDebug>
      <description>POS Design and Management Plug-in</description>
    </file>
    <file>
      <name>EveHQ.Void.dll</name>
      <type>Plug-in</type>
      <version>1.13.2.1021</version>
      <hasDebug>True</hasDebug>
      <description>Wormhole and W-Space Information Tool</description>
    </file>
  </files>
</eveHQUpdate>

